access_cryosphere_data_pool-0.0.1.dev5.dist-info/licenses/LICENSE
datapool/__init__.py
datapool/catalog.py
datapool/loaders.py
access_cryosphere_data_pool-0.0.1.dev5.dist-info/METADATA
access_cryosphere_data_pool-0.0.1.dev5.dist-info/WHEEL
access_cryosphere_data_pool-0.0.1.dev5.dist-info/top_level.txt
access_cryosphere_data_pool-0.0.1.dev5.dist-info/RECORD
