Metadata-Version: 2.4
Name: access-cryosphere-data-pool
Version: 0.0.1.dev5
Summary: Cryosphere Community Datapool (CCD) and associated tools, managed by ACCESS-NRI
Author: ACCESS-NRI
License: Apache-2.0
Project-URL: Homepage, https://github.com/ACCESS-NRI/access-cryosphere-data-pool
Project-URL: Repository, https://github.com/ACCESS-NRI/access-cryosphere-data-pool
Project-URL: Issues, https://github.com/ACCESS-NRI/access-cryosphere-data-pool/issues
Classifier: Development Status :: 2 - Pre-Alpha
Classifier: Programming Language :: Python :: 3
Classifier: License :: OSI Approved :: Apache Software License
Classifier: Operating System :: OS Independent
Requires-Python: >=3.9
License-File: LICENSE
Requires-Dist: xarray
Requires-Dist: pandas
Requires-Dist: geopandas
Requires-Dist: rioxarray
Requires-Dist: numpy
Requires-Dist: PyYAML
Dynamic: license-file
